[{"id":"17","province_id":"20","name":"Kota Ambon"},{"id":"44","province_id":"20","name":"Kabupaten Seram Bagian Barat"},{"id":"46","province_id":"20","name":"Kabupaten Seram Bagian Timur"},{"id":"209","province_id":"20","name":"Kabupaten Buru"},{"id":"210","province_id":"20","name":"Kabupaten Buru Selatan"},{"id":"211","province_id":"20","name":"Kabupaten Kepulauan Aru"},{"id":"239","province_id":"20","name":"Kabupaten Kepulauan Tanimbar (Maluku Tenggara Barat)"},{"id":"347","province_id":"20","name":"Kota Tual"},{"id":"383","province_id":"20","name":"Kabupaten Maluku Barat Daya"},{"id":"384","province_id":"20","name":"Kabupaten Maluku Tengah"},{"id":"385","province_id":"20","name":"Kabupaten Maluku Tenggara"}]