[{"id":"68951","district_id":"1313","name":"Legok"},{"id":"68958","district_id":"1313","name":"Nanggela"},{"id":"69220","district_id":"1313","name":"Bunder"},{"id":"69223","district_id":"1313","name":"Cibulan"},{"id":"69228","district_id":"1313","name":"Cidahu"},{"id":"69238","district_id":"1313","name":"Cieurih"},{"id":"69241","district_id":"1313","name":"Cihideung Girang (Cihideunggirang)"},{"id":"69246","district_id":"1313","name":"Cihideung Hilir (Cihideunghilir)"},{"id":"69251","district_id":"1313","name":"Cikeusik"},{"id":"69255","district_id":"1313","name":"Datar"},{"id":"69264","district_id":"1313","name":"Jatimulya"},{"id":"69274","district_id":"1313","name":"Kertawinangun"}]