[{"id":"67756","district_id":"1316","name":"Susukan"},{"id":"69409","district_id":"1316","name":"Cimaranten"},{"id":"69417","district_id":"1316","name":"Cipicung"},{"id":"69425","district_id":"1316","name":"Karoya"},{"id":"69432","district_id":"1316","name":"Mekarsari"},{"id":"69440","district_id":"1316","name":"Muncangela"},{"id":"69446","district_id":"1316","name":"Pamulihan"},{"id":"69450","district_id":"1316","name":"Salareuma"},{"id":"69456","district_id":"1316","name":"Suganangan"},{"id":"69461","district_id":"1316","name":"Sukamukti"}]