[{"id":"69148","district_id":"1334","name":"Cibuluh"},{"id":"69155","district_id":"1334","name":"Cidamar"},{"id":"69160","district_id":"1334","name":"Cimaragang"},{"id":"69166","district_id":"1334","name":"Cisalak"},{"id":"69173","district_id":"1334","name":"Gelarpawitan"},{"id":"69185","district_id":"1334","name":"Gelarwangi"},{"id":"69190","district_id":"1334","name":"Jayapura"},{"id":"69195","district_id":"1334","name":"Karangwangi"},{"id":"69199","district_id":"1334","name":"Karyabakti"},{"id":"69203","district_id":"1334","name":"Kertajadi"},{"id":"69206","district_id":"1334","name":"Mekarjaya"},{"id":"69209","district_id":"1334","name":"Neglasari"},{"id":"69211","district_id":"1334","name":"Puncakbaru"},{"id":"69213","district_id":"1334","name":"Sukapura"}]