[{"id":"58876","district_id":"1653","name":"Cangkring"},{"id":"58883","district_id":"1653","name":"Dawungan"},{"id":"58892","district_id":"1653","name":"Duren"},{"id":"58898","district_id":"1653","name":"Guno"},{"id":"58907","district_id":"1653","name":"Jatirejo"},{"id":"58913","district_id":"1653","name":"Jatiroto"},{"id":"58939","district_id":"1653","name":"Mojopuro (Mojopura)"},{"id":"58942","district_id":"1653","name":"Ngelo"},{"id":"58946","district_id":"1653","name":"Pengkol"},{"id":"58950","district_id":"1653","name":"Pesido"},{"id":"58955","district_id":"1653","name":"Pingkuk"},{"id":"58970","district_id":"1653","name":"Sanggrong"},{"id":"58977","district_id":"1653","name":"Sugihan"},{"id":"59353","district_id":"1653","name":"Boto"},{"id":"59371","district_id":"1653","name":"Brenggolo"}]