[{"id":"57821","district_id":"1935","name":"Libo Jaya"},{"id":"57867","district_id":"1935","name":"Pencing Bekuto"},{"id":"57871","district_id":"1935","name":"Sam Sam"},{"id":"57885","district_id":"1935","name":"Simpang Belutu"},{"id":"57891","district_id":"1935","name":"Sungai Gondang"},{"id":"57914","district_id":"1935","name":"Telaga Sam-Sam"},{"id":"58609","district_id":"1935","name":"Bekalar"},{"id":"58615","district_id":"1935","name":"Belutu"},{"id":"58621","district_id":"1935","name":"Jambai Makmur"},{"id":"58625","district_id":"1935","name":"Kandis"},{"id":"58656","district_id":"1935","name":"Kandis Kota"}]