[{"id":"52286","district_id":"2351","name":"Pangkung Karung"},{"id":"52304","district_id":"2351","name":"Penarukan"},{"id":"52328","district_id":"2351","name":"Samsam"},{"id":"52335","district_id":"2351","name":"Sembung Gede"},{"id":"52347","district_id":"2351","name":"Tibubiu (Tibu Biu \/ Tibubiyu)"},{"id":"52359","district_id":"2351","name":"Timpag"},{"id":"52374","district_id":"2351","name":"Tista"},{"id":"52565","district_id":"2351","name":"Batuaji"},{"id":"52577","district_id":"2351","name":"Baturiti"},{"id":"52593","district_id":"2351","name":"Belumbang"},{"id":"52611","district_id":"2351","name":"Kelating"},{"id":"52629","district_id":"2351","name":"Kerambitan"},{"id":"52646","district_id":"2351","name":"Kesiut"},{"id":"52656","district_id":"2351","name":"Kukuh"},{"id":"52671","district_id":"2351","name":"Meliling"}]