[{"id":"78470","district_id":"2721","name":"Minanga"},{"id":"78474","district_id":"2721","name":"Mokallang"},{"id":"78482","district_id":"2721","name":"Rantelemo"},{"id":"78487","district_id":"2721","name":"Rantetarima"},{"id":"78490","district_id":"2721","name":"Saluassing"},{"id":"78497","district_id":"2721","name":"Salubulo"},{"id":"78522","district_id":"2721","name":"Saludengen"},{"id":"78530","district_id":"2721","name":"Salukadi"},{"id":"78532","district_id":"2721","name":"Salukepopok"},{"id":"78537","district_id":"2721","name":"Salururu"},{"id":"78538","district_id":"2721","name":"Salutabang"},{"id":"78544","district_id":"2721","name":"Sikamase"},{"id":"78549","district_id":"2721","name":"Tanete Tomba"},{"id":"78556","district_id":"2721","name":"Ulumambi"},{"id":"78564","district_id":"2721","name":"Ulumambi Barat"},{"id":"78684","district_id":"2721","name":"Balatana"},{"id":"78692","district_id":"2721","name":"Bambang"},{"id":"78700","district_id":"2721","name":"Bambang Timur"},{"id":"78741","district_id":"2721","name":"Limbadebata"},{"id":"78749","district_id":"2721","name":"Masoso"}]