[{"id":"50018","district_id":"2935","name":"Candinata"},{"id":"50032","district_id":"2935","name":"Candiwulan"},{"id":"50043","district_id":"2935","name":"Cendana"},{"id":"50055","district_id":"2935","name":"Karangaren"},{"id":"50068","district_id":"2935","name":"Karangcegak"},{"id":"50075","district_id":"2935","name":"Karangjengkol"},{"id":"50085","district_id":"2935","name":"Karangklesem"},{"id":"50091","district_id":"2935","name":"Karanglewas"},{"id":"50105","district_id":"2935","name":"Karangreja"},{"id":"50122","district_id":"2935","name":"Kutasari"},{"id":"50128","district_id":"2935","name":"Limbangan"},{"id":"50138","district_id":"2935","name":"Meri"},{"id":"50151","district_id":"2935","name":"Munjul"},{"id":"50158","district_id":"2935","name":"Sumingkir"}]