[{"id":"49052","district_id":"3376","name":"Jojol"},{"id":"49060","district_id":"3376","name":"Pulauhalang Belakang (Pulau Halang Belakang)"},{"id":"49076","district_id":"3376","name":"Pulauhalang Hulu (Pulau Halang Hulu)"},{"id":"49087","district_id":"3376","name":"Pulauhalang Muka (Pulau Halang Muka)"},{"id":"49136","district_id":"3376","name":"Rantau Panjang Kiri"},{"id":"49147","district_id":"3376","name":"Rantau Panjang Kiri Hilir"},{"id":"49161","district_id":"3376","name":"Sungaimajo (Sei \/ Sungai Majo)"},{"id":"49172","district_id":"3376","name":"Sungaimajo Pusako"},{"id":"49185","district_id":"3376","name":"Sungaipanji-panji (Sei \/ Sungai Panji Panji)"},{"id":"49198","district_id":"3376","name":"Sungaipinang (Sei \/ Sungai Pinang)"},{"id":"49211","district_id":"3376","name":"Teluknilap (Teluk Nilap)"},{"id":"49218","district_id":"3376","name":"Teluknilap Jaya (Teluk Nilap Jaya)"}]