[{"id":"39570","district_id":"3721","name":"Banjarnegoro"},{"id":"39577","district_id":"3721","name":"Banyurojo"},{"id":"39579","district_id":"3721","name":"Bondowoso"},{"id":"39585","district_id":"3721","name":"Bulurejo"},{"id":"39590","district_id":"3721","name":"Danurejo"},{"id":"39595","district_id":"3721","name":"Deyangan"},{"id":"39600","district_id":"3721","name":"Donorojo"},{"id":"39607","district_id":"3721","name":"Jogonegoro"},{"id":"39618","district_id":"3721","name":"Kalinegoro"},{"id":"39656","district_id":"3721","name":"Mertoyudan"},{"id":"39663","district_id":"3721","name":"Pasuruhan"},{"id":"39671","district_id":"3721","name":"Sukorejo"},{"id":"39677","district_id":"3721","name":"Sumberrejo"}]