[{"id":"34906","district_id":"3787","name":"Asemgede (Asem Gede)"},{"id":"34910","district_id":"3787","name":"Cupak"},{"id":"34914","district_id":"3787","name":"Keboan"},{"id":"34920","district_id":"3787","name":"Kedungbogo (Kedung Bogo)"},{"id":"34924","district_id":"3787","name":"Ketapangkuning (Ketapang Kuning)"},{"id":"34933","district_id":"3787","name":"Kromong"},{"id":"34945","district_id":"3787","name":"Manunggal"},{"id":"34947","district_id":"3787","name":"Mojodanu"},{"id":"34949","district_id":"3787","name":"Ngampel"},{"id":"34952","district_id":"3787","name":"Ngusikan"},{"id":"35102","district_id":"3787","name":"Sumbernongko (Sumber Nongko)"}]