[{"id":"31320","district_id":"4020","name":"Air Mesu (Airmesu)"},{"id":"31326","district_id":"4020","name":"Air Mesu Timur"},{"id":"31338","district_id":"4020","name":"Batu Belubang"},{"id":"31349","district_id":"4020","name":"Beluluk"},{"id":"31355","district_id":"4020","name":"Benteng"},{"id":"31362","district_id":"4020","name":"Dul"},{"id":"31371","district_id":"4020","name":"Jeruk"},{"id":"31380","district_id":"4020","name":"Kebintik"},{"id":"31384","district_id":"4020","name":"Mangkol"},{"id":"31393","district_id":"4020","name":"Padang Baru"},{"id":"31401","district_id":"4020","name":"Pedindang (Pelindang \/ Selindung)"},{"id":"31412","district_id":"4020","name":"Tanjung Gunung"}]