[{"id":"41662","district_id":"4107","name":"Maruni"},{"id":"41664","district_id":"4107","name":"Masyepi (Masiepi)"},{"id":"41668","district_id":"4107","name":"Misapmeysi"},{"id":"41672","district_id":"4107","name":"Mupi"},{"id":"41674","district_id":"4107","name":"Ngunimbouw (Ngunibouw)"},{"id":"41678","district_id":"4107","name":"Sowi"},{"id":"41680","district_id":"4107","name":"Waluri (Waruri \/ Weluri)"},{"id":"41684","district_id":"4107","name":"Wamesa"},{"id":"41686","district_id":"4107","name":"Warkomi"},{"id":"41690","district_id":"4107","name":"Warmomi (Warmumi)"},{"id":"41692","district_id":"4107","name":"Warswami (Warsuami)"},{"id":"41694","district_id":"4107","name":"Wasai (Wasay)"},{"id":"44443","district_id":"4107","name":"Acemo"},{"id":"44453","district_id":"4107","name":"Anday"},{"id":"44471","district_id":"4107","name":"Anggresi (Angrisi)"},{"id":"44476","district_id":"4107","name":"Dihara"},{"id":"44483","district_id":"4107","name":"Dobut (Doopud\/Doput)"},{"id":"44486","district_id":"4107","name":"Katebu"}]