[{"id":"33122","district_id":"4619","name":"Jatiwangi"},{"id":"33128","district_id":"4619","name":"Karanganyar"},{"id":"33133","district_id":"4619","name":"Kedungsugih"},{"id":"33140","district_id":"4619","name":"Kertaharja"},{"id":"33142","district_id":"4619","name":"Mulyoharjo"},{"id":"33146","district_id":"4619","name":"Pagerbarang"},{"id":"33151","district_id":"4619","name":"Pesarean"},{"id":"33156","district_id":"4619","name":"Rajegwesi"},{"id":"33160","district_id":"4619","name":"Randusari"},{"id":"33164","district_id":"4619","name":"Semboja"},{"id":"33177","district_id":"4619","name":"Sidamulya (Sido Mulyo)"},{"id":"33186","district_id":"4619","name":"Srengseng"},{"id":"33190","district_id":"4619","name":"Surokidul"}]