[{"id":"22900","district_id":"4627","name":"Panusupan"},{"id":"23001","district_id":"4627","name":"Sumampir"},{"id":"23023","district_id":"4627","name":"Losari"},{"id":"23046","district_id":"4627","name":"Tanalum"},{"id":"23073","district_id":"4627","name":"Makam"},{"id":"23142","district_id":"4627","name":"Wanogara Kulon"},{"id":"23150","district_id":"4627","name":"Wanogara Wetan"},{"id":"23201","district_id":"4627","name":"Wlahar"},{"id":"23316","district_id":"4627","name":"Bantarbarang"},{"id":"23329","district_id":"4627","name":"Bodaskarangjati (Bodas Karangjati)"},{"id":"25182","district_id":"4627","name":"Gunungwuled"},{"id":"25236","district_id":"4627","name":"Karangbawang"}]