[{"id":"21729","district_id":"4964","name":"Jahiang"},{"id":"21735","district_id":"4964","name":"Karangmukti"},{"id":"21746","district_id":"4964","name":"Kawungsari"},{"id":"21754","district_id":"4964","name":"Kutawaringin"},{"id":"21768","district_id":"4964","name":"Margalaksana"},{"id":"21776","district_id":"4964","name":"Neglasari"},{"id":"21783","district_id":"4964","name":"Salawu"},{"id":"21790","district_id":"4964","name":"Serang"},{"id":"21801","district_id":"4964","name":"Sukarasa"},{"id":"21809","district_id":"4964","name":"Sundawenang"},{"id":"21814","district_id":"4964","name":"Tanjungsari"},{"id":"21820","district_id":"4964","name":"Tenjowaringin"}]