[{"id":"26846","district_id":"5074","name":"Babakan"},{"id":"26855","district_id":"5074","name":"Banjar Agung Ilir"},{"id":"26871","district_id":"5074","name":"Banjar Agung Udik"},{"id":"26884","district_id":"5074","name":"Binjai Wangi"},{"id":"26888","district_id":"5074","name":"Campang Way Handak"},{"id":"26897","district_id":"5074","name":"Gading"},{"id":"26905","district_id":"5074","name":"Gunung Kasih"},{"id":"26919","district_id":"5074","name":"Gunung Tiga"},{"id":"26931","district_id":"5074","name":"Kayuhubi"},{"id":"26936","district_id":"5074","name":"Negeri Ratu"},{"id":"26943","district_id":"5074","name":"Pungkut"},{"id":"26956","district_id":"5074","name":"Rantau Tijang"},{"id":"26965","district_id":"5074","name":"Sinar Agung"},{"id":"26974","district_id":"5074","name":"Suka Mulya"},{"id":"26988","district_id":"5074","name":"Sukajadi"},{"id":"26996","district_id":"5074","name":"Sukamaju (Suka Maju)"},{"id":"27004","district_id":"5074","name":"Sumanda"},{"id":"27015","district_id":"5074","name":"Talang Lebar"},{"id":"27023","district_id":"5074","name":"Taman Sari (Tamansari)"},{"id":"27047","district_id":"5074","name":"Tangkit Serdang"},{"id":"27055","district_id":"5074","name":"Tanjung Agung"},{"id":"27077","district_id":"5074","name":"Tanjung Heran"},{"id":"27082","district_id":"5074","name":"Tanjung Kemala"},{"id":"27088","district_id":"5074","name":"Tiuh Memon"},{"id":"27095","district_id":"5074","name":"Way Jaha"},{"id":"27101","district_id":"5074","name":"Way Manak"},{"id":"27111","district_id":"5074","name":"Way Piring"}]