[{"id":"32905","district_id":"5128","name":"Sumber Rejo"},{"id":"32917","district_id":"5128","name":"Tanjung Dalam\/Dalom"},{"id":"32924","district_id":"5128","name":"Way Ngison (Way Ngisom)"},{"id":"33226","district_id":"5128","name":"Bumi Ratu"},{"id":"33230","district_id":"5128","name":"Bumi Rejo"},{"id":"33248","district_id":"5128","name":"Candi Retno"},{"id":"33274","district_id":"5128","name":"Ganjaran"},{"id":"33286","district_id":"5128","name":"Gemah Ripah"},{"id":"33290","district_id":"5128","name":"Gumuk Mas"},{"id":"33297","district_id":"5128","name":"Gumukrejo (Gumuk Rejo)"},{"id":"35196","district_id":"5128","name":"Karangsari"},{"id":"35217","district_id":"5128","name":"Lugusari"},{"id":"35267","district_id":"5128","name":"Padang Rejo"},{"id":"35285","district_id":"5128","name":"Pagelaran"},{"id":"35287","district_id":"5128","name":"Pamenang"},{"id":"35300","district_id":"5128","name":"Panutan"},{"id":"35303","district_id":"5128","name":"Pasir Ukir"},{"id":"35311","district_id":"5128","name":"Patoman"},{"id":"35317","district_id":"5128","name":"Puji Harjo"},{"id":"35330","district_id":"5128","name":"Sidodadi"},{"id":"35352","district_id":"5128","name":"Suka Ratu (Sukaratu)"},{"id":"35354","district_id":"5128","name":"Suka Wangi (Sukawangi)"}]