[{"id":"27324","district_id":"5139","name":"Bode Lor"},{"id":"27328","district_id":"5139","name":"Bodesari"},{"id":"27334","district_id":"5139","name":"Cempaka"},{"id":"27339","district_id":"5139","name":"Danamulya"},{"id":"27342","district_id":"5139","name":"Gombang"},{"id":"27353","district_id":"5139","name":"Karangasem"},{"id":"27360","district_id":"5139","name":"Karangmulya"},{"id":"27383","district_id":"5139","name":"Kebarepan"},{"id":"27414","district_id":"5139","name":"Kedungsana"},{"id":"27419","district_id":"5139","name":"Lurah"},{"id":"27432","district_id":"5139","name":"Marikangen"},{"id":"27443","district_id":"5139","name":"Pamijahan"},{"id":"27456","district_id":"5139","name":"Pasanggrahan"},{"id":"27464","district_id":"5139","name":"Plumbon"},{"id":"27489","district_id":"5139","name":"Purbawinangun"}]