[{"id":"24261","district_id":"5260","name":"Purwoasri"},{"id":"24264","district_id":"5260","name":"Purwodadi"},{"id":"24266","district_id":"5260","name":"Sidomulyo"},{"id":"24269","district_id":"5260","name":"Sumberjo"},{"id":"24272","district_id":"5260","name":"Tugu"},{"id":"24274","district_id":"5260","name":"Wonotengah"},{"id":"24277","district_id":"5260","name":"Woromarto"},{"id":"24574","district_id":"5260","name":"Muneng"},{"id":"24582","district_id":"5260","name":"Pandansari"},{"id":"24588","district_id":"5260","name":"Pesing"},{"id":"24743","district_id":"5260","name":"Belor"},{"id":"24754","district_id":"5260","name":"Blawe"},{"id":"24764","district_id":"5260","name":"Bulu"},{"id":"24771","district_id":"5260","name":"Dawuhan"},{"id":"24782","district_id":"5260","name":"Dayu"},{"id":"24789","district_id":"5260","name":"Jantok"},{"id":"24796","district_id":"5260","name":"Karangpakis"},{"id":"24802","district_id":"5260","name":"Kempleng"},{"id":"24809","district_id":"5260","name":"Ketawang"},{"id":"24820","district_id":"5260","name":"Klampitan"},{"id":"24831","district_id":"5260","name":"Mekikis"},{"id":"24841","district_id":"5260","name":"Merjoyo"},{"id":"24852","district_id":"5260","name":"Mranggen"}]