[{"id":"19972","district_id":"5361","name":"Apas"},{"id":"19988","district_id":"5361","name":"Bebanas"},{"id":"20004","district_id":"5361","name":"Harapan"},{"id":"20023","district_id":"5361","name":"Kekayap"},{"id":"20034","district_id":"5361","name":"Kunyit"},{"id":"20049","district_id":"5361","name":"Lulu"},{"id":"20059","district_id":"5361","name":"Melasu Baru"},{"id":"20069","district_id":"5361","name":"Pembeliangan"},{"id":"20080","district_id":"5361","name":"Sujau"},{"id":"20091","district_id":"5361","name":"Tetaban"}]