[{"id":"23691","district_id":"5432","name":"Bagik Manis"},{"id":"23700","district_id":"5432","name":"Belanting"},{"id":"23714","district_id":"5432","name":"Dadap"},{"id":"23729","district_id":"5432","name":"Darakunci"},{"id":"23743","district_id":"5432","name":"Labuhan Pandan"},{"id":"23762","district_id":"5432","name":"Madayin"},{"id":"23776","district_id":"5432","name":"Obel Obel"},{"id":"23786","district_id":"5432","name":"Padak Guar"},{"id":"23808","district_id":"5432","name":"Sambalia (Sambelia)"},{"id":"23820","district_id":"5432","name":"Senanggalih"},{"id":"23828","district_id":"5432","name":"Sugian"}]