[{"id":"10641","district_id":"5742","name":"Taman Roya"},{"id":"10662","district_id":"5742","name":"Tonro Kassi (Tonrokassi)"},{"id":"10678","district_id":"5742","name":"Tonro Kassi Barat (Tonrokassi Barat)"},{"id":"10696","district_id":"5742","name":"Tonro Kassi Timur (Tonrokassi Timur)"},{"id":"10711","district_id":"5742","name":"Turatea"},{"id":"10829","district_id":"5742","name":"Bonto Tangnga (Bontotangnga)"},{"id":"10838","district_id":"5742","name":"Bontojai"},{"id":"10852","district_id":"5742","name":"Bontosunggu"},{"id":"10881","district_id":"5742","name":"Borongtala"},{"id":"10891","district_id":"5742","name":"Karelayu"},{"id":"10897","district_id":"5742","name":"Manjangloe"},{"id":"10903","district_id":"5742","name":"Turatea Timur"}]