[{"id":"77282","district_id":"604","name":"Sokanandi"},{"id":"77289","district_id":"604","name":"Sokayasa"},{"id":"77295","district_id":"604","name":"Tlagawera"},{"id":"77301","district_id":"604","name":"Wangon"},{"id":"77858","district_id":"604","name":"Ampelsari"},{"id":"77868","district_id":"604","name":"Argasoka"},{"id":"77874","district_id":"604","name":"Cendana"},{"id":"77880","district_id":"604","name":"Karangtengah"},{"id":"77886","district_id":"604","name":"Krandegan"},{"id":"77889","district_id":"604","name":"Kutabanjarnegara (Kuta Banjarnegara)"},{"id":"77894","district_id":"604","name":"Parakancanggah"},{"id":"77897","district_id":"604","name":"Semampir"},{"id":"77902","district_id":"604","name":"Semarang"}]