[{"id":"6565","district_id":"6305","name":"Berlian"},{"id":"6571","district_id":"6305","name":"Bongohulawa (Bongohulowa)"},{"id":"6576","district_id":"6305","name":"Bongoime"},{"id":"6591","district_id":"6305","name":"Bongopini"},{"id":"6601","district_id":"6305","name":"Butu"},{"id":"6614","district_id":"6305","name":"Iloheluma"},{"id":"6623","district_id":"6305","name":"Lonuo"},{"id":"6631","district_id":"6305","name":"Motilango (Mootilango)"},{"id":"6637","district_id":"6305","name":"Moutong"},{"id":"6645","district_id":"6305","name":"Permata"},{"id":"6678","district_id":"6305","name":"Tamboo"},{"id":"6688","district_id":"6305","name":"Toto Utara"},{"id":"6695","district_id":"6305","name":"Tunggulo"},{"id":"6707","district_id":"6305","name":"Tunggulo Selatan"}]