[{"id":"8362","district_id":"6400","name":"Bangkal Tengah"},{"id":"8367","district_id":"6400","name":"Jaruju"},{"id":"8372","district_id":"6400","name":"Jaruju Laut"},{"id":"8379","district_id":"6400","name":"Layap Baru"},{"id":"8385","district_id":"6400","name":"Mekar Sari"},{"id":"8388","district_id":"6400","name":"Pandan Sari"},{"id":"8393","district_id":"6400","name":"Pemangkih Baru"},{"id":"8398","district_id":"6400","name":"Pemangkih Darat"},{"id":"8402","district_id":"6400","name":"Pemangkih Tengah"},{"id":"8407","district_id":"6400","name":"Taibah Raya"},{"id":"8413","district_id":"6400","name":"Tampang Awang"},{"id":"8436","district_id":"6400","name":"Tatah Bangkal"},{"id":"8441","district_id":"6400","name":"Tatah Layap"}]