[{"id":"752","district_id":"6684","name":"Brayo"},{"id":"763","district_id":"6684","name":"Brokoh"},{"id":"771","district_id":"6684","name":"Dringo"},{"id":"811","district_id":"6684","name":"Gringgingsari"},{"id":"839","district_id":"6684","name":"Kedungmalang"},{"id":"845","district_id":"6684","name":"Kemligi"},{"id":"853","district_id":"6684","name":"Kreyo"},{"id":"867","district_id":"6684","name":"Penangkan"},{"id":"875","district_id":"6684","name":"Sendang"},{"id":"995","district_id":"6684","name":"Sigayam"},{"id":"1011","district_id":"6684","name":"Silurah"},{"id":"1062","district_id":"6684","name":"Siwatu"},{"id":"1096","district_id":"6684","name":"Sodong"},{"id":"1143","district_id":"6684","name":"Wates"},{"id":"1152","district_id":"6684","name":"Wonotunggal"}]