[{"id":"7036","district_id":"6857","name":"Buntul Musara"},{"id":"7041","district_id":"6857","name":"Kuala Jernih"},{"id":"7047","district_id":"6857","name":"Pasir"},{"id":"7052","district_id":"6857","name":"Perlak"},{"id":"7059","district_id":"6857","name":"Pulo Gelime"},{"id":"7066","district_id":"6857","name":"Rerebe"},{"id":"7074","district_id":"6857","name":"Setul"},{"id":"7079","district_id":"6857","name":"UPT. Pantan Kela (Pantan Kela)"},{"id":"7088","district_id":"6857","name":"UPT. Paya Kumer (Paya Kumer)"},{"id":"7097","district_id":"6857","name":"Uyem Beriring"}]