[{"id":"76836","district_id":"964","name":"Siolip"},{"id":"76847","district_id":"964","name":"Sitarolo Julu"},{"id":"77053","district_id":"964","name":"Binabo Jae"},{"id":"77061","district_id":"964","name":"Binabo Julu"},{"id":"77066","district_id":"964","name":"Hasahatan Jae"},{"id":"77072","district_id":"964","name":"Hasahatan Julu"},{"id":"77079","district_id":"964","name":"Limbong"},{"id":"77087","district_id":"964","name":"Mompang"},{"id":"77092","district_id":"964","name":"Saba Rimba\/Riba"},{"id":"77098","district_id":"964","name":"Sabahotang"},{"id":"77101","district_id":"964","name":"Sigorbus Jae"},{"id":"77108","district_id":"964","name":"Sigorbus Julu"},{"id":"77114","district_id":"964","name":"Simaninggir"}]