[{"id":"168","regency_id":"374","name":"Bendo"},{"id":"780","regency_id":"374","name":"Barat"},{"id":"2442","regency_id":"374","name":"Karangrejo"},{"id":"2510","regency_id":"374","name":"Karas"},{"id":"2687","regency_id":"374","name":"Kartoharjo (Kertoharjo)"},{"id":"3051","regency_id":"374","name":"Kawedanan"},{"id":"3094","regency_id":"374","name":"Lembeyan"},{"id":"3184","regency_id":"374","name":"Maospati"},{"id":"3321","regency_id":"374","name":"Magetan"},{"id":"3752","regency_id":"374","name":"Nguntoronadi"},{"id":"3865","regency_id":"374","name":"Panekan"},{"id":"3995","regency_id":"374","name":"Ngariboyo"},{"id":"4140","regency_id":"374","name":"Parang"},{"id":"5006","regency_id":"374","name":"Poncol"},{"id":"5009","regency_id":"374","name":"Plaosan"},{"id":"5686","regency_id":"374","name":"Sukomoro"},{"id":"6019","regency_id":"374","name":"Sidorejo"},{"id":"6139","regency_id":"374","name":"Takeran"}]