[{"id":"173","regency_id":"491","name":"Batulappa (Batu Lappa)"},{"id":"1326","regency_id":"491","name":"Cempa"},{"id":"1487","regency_id":"491","name":"Duampanua"},{"id":"2975","regency_id":"491","name":"Lembang"},{"id":"3030","regency_id":"491","name":"Mattiro Bulu"},{"id":"3036","regency_id":"491","name":"Mattiro Sompe (Matirro Sompe)"},{"id":"3316","regency_id":"491","name":"Lansirang (Lanrisang)"},{"id":"3890","regency_id":"491","name":"Paleteang"},{"id":"4204","regency_id":"491","name":"Patampanua"},{"id":"5794","regency_id":"491","name":"Suppa"},{"id":"6527","regency_id":"491","name":"Tiroang"},{"id":"7241","regency_id":"491","name":"Watang Sawitto (Watang Sawito)"}]