[{"id":"109","regency_id":"503","name":"Amungkalpia"},{"id":"578","regency_id":"503","name":"Beoga"},{"id":"584","regency_id":"503","name":"Beoga Barat"},{"id":"599","regency_id":"503","name":"Beoga Timur"},{"id":"658","regency_id":"503","name":"Bina"},{"id":"1387","regency_id":"503","name":"Doufo"},{"id":"1586","regency_id":"503","name":"Dervos"},{"id":"1603","regency_id":"503","name":"Gome"},{"id":"1608","regency_id":"503","name":"Gome Utara"},{"id":"1988","regency_id":"503","name":"Erelmakawia"},{"id":"2162","regency_id":"503","name":"Ilaga"},{"id":"2167","regency_id":"503","name":"Ilaga Utara"},{"id":"2374","regency_id":"503","name":"Kembru"},{"id":"2772","regency_id":"503","name":"Agandugume"},{"id":"2787","regency_id":"503","name":"Lambewi"},{"id":"3264","regency_id":"503","name":"Mage'abume"},{"id":"3790","regency_id":"503","name":"Mabugi"},{"id":"4068","regency_id":"503","name":"Ogamanim"},{"id":"4344","regency_id":"503","name":"Omukia"},{"id":"4394","regency_id":"503","name":"Oneri"},{"id":"5323","regency_id":"503","name":"Pogoma"},{"id":"6378","regency_id":"503","name":"Sinak"},{"id":"6389","regency_id":"503","name":"Sinak Barat"},{"id":"6952","regency_id":"503","name":"Wangbe"},{"id":"7193","regency_id":"503","name":"Yugumuak"}]