[{"id":"1704102001","district_id":"170410","name":"Bangun Jiwa"},{"id":"1704102008","district_id":"170410","name":"Benua Ratu"},{"id":"1704102002","district_id":"170410","name":"Cahaya Negeri\/Negri"},{"id":"1704102005","district_id":"170410","name":"Durian Besar"},{"id":"1704102004","district_id":"170410","name":"Ganda Suli (Gindo Suli)"},{"id":"1704102010","district_id":"170410","name":"Kepahyang"},{"id":"1704102003","district_id":"170410","name":"Padang Jati"},{"id":"1704102011","district_id":"170410","name":"Pulau Panggung (Pulang Panggung)"},{"id":"1704102012","district_id":"170410","name":"Serdang Indah"},{"id":"1704102006","district_id":"170410","name":"Tanjung Beringin"},{"id":"1704102009","district_id":"170410","name":"Tuguk (Puguk)"},{"id":"1704102007","district_id":"170410","name":"Umbul"}]