[{"id":"53632","district_id":"2057","name":"Ambal Ambil"},{"id":"53637","district_id":"2057","name":"Benerwojo"},{"id":"53638","district_id":"2057","name":"Wrati"},{"id":"53643","district_id":"2057","name":"Cobanjoyo (Coban Joyo)"},{"id":"53649","district_id":"2057","name":"Kedemungan"},{"id":"53658","district_id":"2057","name":"Kedungpengaron (Kedung Pengaron)"},{"id":"53662","district_id":"2057","name":"Kejayan"},{"id":"53670","district_id":"2057","name":"Kepuh"},{"id":"53678","district_id":"2057","name":"Ketangirejo (Ketangi Rejo \/ Kangirejo)"},{"id":"53687","district_id":"2057","name":"Klangrong"},{"id":"53696","district_id":"2057","name":"Klinter"},{"id":"53704","district_id":"2057","name":"Kurung"},{"id":"53713","district_id":"2057","name":"Linggo"},{"id":"53729","district_id":"2057","name":"Lorokan"},{"id":"53736","district_id":"2057","name":"Luwuk"},{"id":"53743","district_id":"2057","name":"Oro Oro Puleh (Oro Oro Pule)"},{"id":"53748","district_id":"2057","name":"Pacar Keling"},{"id":"53756","district_id":"2057","name":"Patebon"},{"id":"53770","district_id":"2057","name":"Randugong (Randu Gong)"},{"id":"53779","district_id":"2057","name":"Sladi"},{"id":"53787","district_id":"2057","name":"Sumber Banteng"},{"id":"53796","district_id":"2057","name":"Sumber Suko"},{"id":"53804","district_id":"2057","name":"Tanggulangin"},{"id":"53813","district_id":"2057","name":"Tundosuro\/Tundosor o"},{"id":"53822","district_id":"2057","name":"Wangkalwetan (Wangkal Wetan)"}]