[{"id":"56456","district_id":"2359","name":"Bogiyoteugi"},{"id":"56459","district_id":"2359","name":"Botumuma (Botumoma)"},{"id":"56468","district_id":"2359","name":"Digikebo"},{"id":"56471","district_id":"2359","name":"Matadi"},{"id":"56484","district_id":"2359","name":"Obaibega"},{"id":"56490","district_id":"2359","name":"Pouwouda (Pouwoda \/ Pouwuoda)"},{"id":"56492","district_id":"2359","name":"Puweta\/Pueta I"},{"id":"56496","district_id":"2359","name":"Puweta\/Pueta II"},{"id":"56499","district_id":"2359","name":"Tuwaida"},{"id":"56501","district_id":"2359","name":"Ugikagouda"},{"id":"56505","district_id":"2359","name":"Ugikebo"},{"id":"56507","district_id":"2359","name":"Yepo (Makidimi)"}]