[{"id":"48819","district_id":"2821","name":"Bangkudu (Ereke)"},{"id":"48825","district_id":"2821","name":"Banu-Banua Jaya"},{"id":"48831","district_id":"2821","name":"Bonelipu"},{"id":"48841","district_id":"2821","name":"Eelahaji"},{"id":"48863","district_id":"2821","name":"Jampaka"},{"id":"48874","district_id":"2821","name":"Kadacua"},{"id":"48879","district_id":"2821","name":"Kalibu"},{"id":"48893","district_id":"2821","name":"Laangke"},{"id":"48902","district_id":"2821","name":"Lakonea"},{"id":"48908","district_id":"2821","name":"Lantagi"},{"id":"48917","district_id":"2821","name":"Lemo (Bonerombo)"},{"id":"48923","district_id":"2821","name":"Lemo Ea"},{"id":"48929","district_id":"2821","name":"Linsowu"},{"id":"48938","district_id":"2821","name":"Lipu"},{"id":"48948","district_id":"2821","name":"Loji"},{"id":"48961","district_id":"2821","name":"Malalanda"},{"id":"48968","district_id":"2821","name":"Rombo"},{"id":"48976","district_id":"2821","name":"Sara'ea"},{"id":"48982","district_id":"2821","name":"Tomoahi"},{"id":"48992","district_id":"2821","name":"Triwacuwacu (Tri Wacu-Wacu)"},{"id":"49003","district_id":"2821","name":"Waculaea"},{"id":"49022","district_id":"2821","name":"Wandaka"},{"id":"49033","district_id":"2821","name":"Wasalabose"}]