[{"id":"46301","district_id":"3201","name":"Cempeh"},{"id":"46308","district_id":"3201","name":"Langgengsari"},{"id":"46311","district_id":"3201","name":"Lelea"},{"id":"46317","district_id":"3201","name":"Nunuk"},{"id":"46324","district_id":"3201","name":"Pangauban"},{"id":"46330","district_id":"3201","name":"Tamansari"},{"id":"46332","district_id":"3201","name":"Tegalasari (Telagasari)"},{"id":"46342","district_id":"3201","name":"Tempel"},{"id":"46354","district_id":"3201","name":"Tempelkulon"},{"id":"46363","district_id":"3201","name":"Tugu"},{"id":"46367","district_id":"3201","name":"Tunggul Payung (Tunggulpayung)"}]