[{"id":"74078","district_id":"335","name":"Aneya"},{"id":"74095","district_id":"335","name":"Biandoga"},{"id":"74109","district_id":"335","name":"Bugalaga"},{"id":"74115","district_id":"335","name":"Danggatadi"},{"id":"74168","district_id":"335","name":"Kalawa"},{"id":"74182","district_id":"335","name":"Kigitadi"},{"id":"74196","district_id":"335","name":"Maniuwo"},{"id":"74215","district_id":"335","name":"Maolagi"},{"id":"74229","district_id":"335","name":"Moyomataga"},{"id":"74260","district_id":"335","name":"Ndabatadi"},{"id":"74275","district_id":"335","name":"Pagamba"},{"id":"74305","district_id":"335","name":"Pitadi"},{"id":"74327","district_id":"335","name":"Tunggapo"},{"id":"74341","district_id":"335","name":"Ular Merah"},{"id":"74356","district_id":"335","name":"Yagaito"},{"id":"74367","district_id":"335","name":"Yanei"}]