[{"id":"43226","district_id":"3469","name":"Tellulimpoe"},{"id":"43719","district_id":"3469","name":"Attang Salo"},{"id":"43733","district_id":"3469","name":"Batu-Batu"},{"id":"43752","district_id":"3469","name":"Bulue"},{"id":"43766","district_id":"3469","name":"Kaca"},{"id":"43783","district_id":"3469","name":"Laringgi"},{"id":"43800","district_id":"3469","name":"Limpomajang"},{"id":"43815","district_id":"3469","name":"Manorang Salo"},{"id":"43822","district_id":"3469","name":"Panincong"},{"id":"43831","district_id":"3469","name":"Patampanua"}]