[{"id":"39240","district_id":"3517","name":"Arahan"},{"id":"39249","district_id":"3517","name":"Banjar Sari"},{"id":"39265","district_id":"3517","name":"Cempaka Wangi"},{"id":"39300","district_id":"3517","name":"Gedung Agung"},{"id":"39309","district_id":"3517","name":"Gunung Kembang"},{"id":"39315","district_id":"3517","name":"Lebuay Bandung"},{"id":"39321","district_id":"3517","name":"Lematang Jaya"},{"id":"39326","district_id":"3517","name":"Muara Lawai"},{"id":"39333","district_id":"3517","name":"Nanjungan"},{"id":"39341","district_id":"3517","name":"Prabu Menang"},{"id":"39351","district_id":"3517","name":"Sengkuang"},{"id":"39376","district_id":"3517","name":"Sirah Pulau"},{"id":"39386","district_id":"3517","name":"Tanjung Jambu"},{"id":"39396","district_id":"3517","name":"Tanjung Lontar"}]