[{"id":"44761","district_id":"3683","name":"Kelombok"},{"id":"44787","district_id":"3683","name":"Kelumu"},{"id":"44796","district_id":"3683","name":"Mentuda"},{"id":"44807","district_id":"3683","name":"Mepar"},{"id":"44833","district_id":"3683","name":"Merawang"},{"id":"44842","district_id":"3683","name":"Musai"},{"id":"44850","district_id":"3683","name":"Nerekeh"},{"id":"44858","district_id":"3683","name":"Panggak Darat"},{"id":"44865","district_id":"3683","name":"Panggak Laut"},{"id":"44872","district_id":"3683","name":"Pekajang"},{"id":"45554","district_id":"3683","name":"Daik"},{"id":"45563","district_id":"3683","name":"Daik Sepincan"}]