[{"id":"80126","district_id":"388","name":"Marlasi"},{"id":"80140","district_id":"388","name":"Mesidang"},{"id":"80150","district_id":"388","name":"Selmona"},{"id":"80163","district_id":"388","name":"Tasinwaha (Tasin Waha)"},{"id":"80174","district_id":"388","name":"Wahangula-Ngula (Wahangulangula)"},{"id":"80184","district_id":"388","name":"Wahayum \/ Wahayun"},{"id":"80192","district_id":"388","name":"Warialau"},{"id":"80988","district_id":"388","name":"Foket"},{"id":"80998","district_id":"388","name":"Jerwatu"},{"id":"81008","district_id":"388","name":"Kabufin"},{"id":"81018","district_id":"388","name":"Kaibolafin"},{"id":"81033","district_id":"388","name":"Kolamar"}]