[{"id":"71651","district_id":"419","name":"Air Kelian"},{"id":"71696","district_id":"419","name":"Danau Jaya"},{"id":"71720","district_id":"419","name":"Durian Sembilan"},{"id":"71731","district_id":"419","name":"Karet Jaya"},{"id":"71741","district_id":"419","name":"Kembang Tinggi"},{"id":"71763","district_id":"419","name":"Kota Way"},{"id":"71772","district_id":"419","name":"Mekar Jaya"},{"id":"71782","district_id":"419","name":"Serakat Jaya"},{"id":"71847","district_id":"419","name":"Sido Rahayu"},{"id":"71856","district_id":"419","name":"Sidodadi"},{"id":"71863","district_id":"419","name":"Sinar Baru"},{"id":"71870","district_id":"419","name":"Sinar Napalan"},{"id":"71878","district_id":"419","name":"Sipin"},{"id":"71901","district_id":"419","name":"Sri Menanti"},{"id":"71912","district_id":"419","name":"Sumber Raya"},{"id":"71930","district_id":"419","name":"Sumber Ringin"},{"id":"71941","district_id":"419","name":"Talang Padang"},{"id":"71955","district_id":"419","name":"Tanjung Baru"},{"id":"71962","district_id":"419","name":"Tanjung Durian"},{"id":"71974","district_id":"419","name":"Tanjung Jaya"},{"id":"71980","district_id":"419","name":"Tanjung Menang"},{"id":"71993","district_id":"419","name":"Tanjung Sari"}]