[{"id":"33228","district_id":"4399","name":"Aleuti"},{"id":"33235","district_id":"4399","name":"Alosika"},{"id":"33239","district_id":"4399","name":"Atodopi"},{"id":"33246","district_id":"4399","name":"Garuda"},{"id":"33249","district_id":"4399","name":"Langgea"},{"id":"33256","district_id":"4399","name":"Matahori"},{"id":"33264","district_id":"4399","name":"Matanggorai"},{"id":"33266","district_id":"4399","name":"Mekar Jaya"},{"id":"33270","district_id":"4399","name":"Padang Mekar"},{"id":"33276","district_id":"4399","name":"Padangguni"},{"id":"33280","district_id":"4399","name":"Sambaosu"}]