[{"id":"22586","district_id":"4718","name":"Air Jernih"},{"id":"22595","district_id":"4718","name":"Alang Kepayang"},{"id":"22604","district_id":"4718","name":"Barangan"},{"id":"22613","district_id":"4718","name":"Bukit Petaling"},{"id":"22623","district_id":"4718","name":"Danau Baru"},{"id":"22628","district_id":"4718","name":"Danau Tiga"},{"id":"22632","district_id":"4718","name":"Kota Lama"},{"id":"22637","district_id":"4718","name":"Pekan Heran"},{"id":"22646","district_id":"4718","name":"Pematang Jaya"},{"id":"22654","district_id":"4718","name":"Pematang Reba"},{"id":"22664","district_id":"4718","name":"Rantau Bakung"},{"id":"22673","district_id":"4718","name":"Redang"},{"id":"22682","district_id":"4718","name":"Sialang Dua Dahan"},{"id":"22688","district_id":"4718","name":"Sungai Baung"},{"id":"22694","district_id":"4718","name":"Sungai Dawu"},{"id":"22699","district_id":"4718","name":"Talang Jerinjing"},{"id":"22705","district_id":"4718","name":"Tanah Datar"},{"id":"22714","district_id":"4718","name":"Tani Makmur (Tanah Makmur)"}]