[{"id":"21237","district_id":"4747","name":"Golo Leleng"},{"id":"21263","district_id":"4747","name":"Golo Manting"},{"id":"21286","district_id":"4747","name":"Golo Mbu"},{"id":"21308","district_id":"4747","name":"Golo Ndaring"},{"id":"21318","district_id":"4747","name":"Golo Sengang"},{"id":"21331","district_id":"4747","name":"Matawae"},{"id":"21384","district_id":"4747","name":"Nampar Macing"},{"id":"21397","district_id":"4747","name":"Poco Golo Kempo"},{"id":"21411","district_id":"4747","name":"Pulau Nuncung"},{"id":"21418","district_id":"4747","name":"Sano Nggoang"},{"id":"21439","district_id":"4747","name":"Wae Lolos"},{"id":"21453","district_id":"4747","name":"Wae Sano"},{"id":"21472","district_id":"4747","name":"Watu Panggal"},{"id":"21506","district_id":"4747","name":"Golo Kempo"},{"id":"21525","district_id":"4747","name":"Golo Kondeng"}]