[{"id":"25718","district_id":"5393","name":"Beting"},{"id":"25722","district_id":"5393","name":"Bungur"},{"id":"25725","district_id":"5393","name":"Kayu Ara"},{"id":"25728","district_id":"5393","name":"Kedabu Rapat"},{"id":"25731","district_id":"5393","name":"Sendaur"},{"id":"25734","district_id":"5393","name":"Sokop"},{"id":"25738","district_id":"5393","name":"Sonde"},{"id":"25742","district_id":"5393","name":"Tanah Merah"},{"id":"25745","district_id":"5393","name":"Tanjung Kedabu"},{"id":"25748","district_id":"5393","name":"Telesung"},{"id":"25751","district_id":"5393","name":"Tenggayun Raya"}]