[{"id":"17471","district_id":"5440","name":"Bandar Padang"},{"id":"17480","district_id":"5440","name":"Beligan"},{"id":"17488","district_id":"5440","name":"Bukit Meranti"},{"id":"17496","district_id":"5440","name":"Buluh Rampai"},{"id":"17507","district_id":"5440","name":"Kelesa"},{"id":"17513","district_id":"5440","name":"Pangkalan Kasai"},{"id":"17521","district_id":"5440","name":"Paya Rumbai (Payarumbai)"},{"id":"17529","district_id":"5440","name":"Petala Bumi"},{"id":"17545","district_id":"5440","name":"Seresam (Serasam)"},{"id":"17551","district_id":"5440","name":"Sibabat"},{"id":"17556","district_id":"5440","name":"Titian Resak"}]