[{"id":"13209","district_id":"5652","name":"Rogojati"},{"id":"13223","district_id":"5652","name":"Sempol"},{"id":"13308","district_id":"5652","name":"Sukoharjo"},{"id":"13566","district_id":"5652","name":"Suroyudan"},{"id":"13576","district_id":"5652","name":"Tlogo"},{"id":"13796","district_id":"5652","name":"Plodongan"},{"id":"13817","district_id":"5652","name":"Pucungwetan (Pucung Wetan)"},{"id":"13836","district_id":"5652","name":"Pulus"},{"id":"13840","district_id":"5652","name":"Garunglor"},{"id":"13859","district_id":"5652","name":"Gumiwang"},{"id":"13863","district_id":"5652","name":"Gunungtugel"},{"id":"13870","district_id":"5652","name":"Jebengplampitan"},{"id":"13892","district_id":"5652","name":"Kajeksan"},{"id":"13903","district_id":"5652","name":"Kalibening"},{"id":"13942","district_id":"5652","name":"Karanganyar"},{"id":"15151","district_id":"5652","name":"Kupangan"},{"id":"15161","district_id":"5652","name":"Mergosari"}]