[{"id":"859","district_id":"6748","name":"Wee Rame"},{"id":"1465","district_id":"6748","name":"Kanelu"},{"id":"1482","district_id":"6748","name":"Kiku Booko"},{"id":"1509","district_id":"6748","name":"Lete Wungana"},{"id":"1531","district_id":"6748","name":"Limbu Watu"},{"id":"1546","district_id":"6748","name":"Lombu"},{"id":"1575","district_id":"6748","name":"Mata Lombu"},{"id":"1586","district_id":"6748","name":"Mata Wee Karoro"},{"id":"1607","district_id":"6748","name":"Mereda Wuni"},{"id":"1620","district_id":"6748","name":"Omba Rade"},{"id":"1639","district_id":"6748","name":"Bolora"},{"id":"1646","district_id":"6748","name":"Tanggaba"},{"id":"1655","district_id":"6748","name":"Bondo Delo"},{"id":"1664","district_id":"6748","name":"Eka Pata"},{"id":"1666","district_id":"6748","name":"Tarra Mata"},{"id":"1673","district_id":"6748","name":"Gollu Sapi"},{"id":"1683","district_id":"6748","name":"Wee Kokora"},{"id":"1686","district_id":"6748","name":"Kadi Roma"},{"id":"1693","district_id":"6748","name":"Wee Patando"},{"id":"1707","district_id":"6748","name":"Kalingara"}]