[{"id":"3365","district_id":"6925","name":"Cikareo Selatan"},{"id":"3379","district_id":"6925","name":"Cikareo Utara"},{"id":"3391","district_id":"6925","name":"Cilengkrang"},{"id":"3399","district_id":"6925","name":"Cimungkal"},{"id":"3413","district_id":"6925","name":"Cisurat"},{"id":"3418","district_id":"6925","name":"Ganjaresik"},{"id":"3425","district_id":"6925","name":"Mulyajaya"},{"id":"3429","district_id":"6925","name":"Sukajadi"},{"id":"3448","district_id":"6925","name":"Sukapura"},{"id":"3493","district_id":"6925","name":"Wado"}]