[{"id":"80836","district_id":"779","name":"Aralle"},{"id":"80853","district_id":"779","name":"Aralle Selatan"},{"id":"80865","district_id":"779","name":"Aralle Utara"},{"id":"80872","district_id":"779","name":"Baruru"},{"id":"80887","district_id":"779","name":"Hahangan"},{"id":"80892","district_id":"779","name":"Kalabe"},{"id":"80901","district_id":"779","name":"Pamoseang Pangga"},{"id":"80927","district_id":"779","name":"Panetean"},{"id":"80931","district_id":"779","name":"Ralle Anak"},{"id":"80942","district_id":"779","name":"Ralleanak Utara"},{"id":"80951","district_id":"779","name":"Uhaidaho"},{"id":"80969","district_id":"779","name":"Uhailanu"}]