[{"id":"70182","district_id":"798","name":"Candipuro"},{"id":"70201","district_id":"798","name":"Jarit"},{"id":"70211","district_id":"798","name":"Jugosari"},{"id":"70225","district_id":"798","name":"Klopo Sawit (Kloposawit)"},{"id":"70231","district_id":"798","name":"Penanggal"},{"id":"70280","district_id":"798","name":"Sumber Mujur (Sumbermujur)"},{"id":"70292","district_id":"798","name":"Sumber Wuluh (Sumberrejo)"},{"id":"70307","district_id":"798","name":"Sumberejo (Sumberwuluh)"},{"id":"70317","district_id":"798","name":"Tambahrejo"},{"id":"70354","district_id":"798","name":"Tumpeng"}]