[{"id":"100","regency_id":"240","name":"Arjawinangun"},{"id":"343","regency_id":"240","name":"Babakan"},{"id":"483","regency_id":"240","name":"Beber"},{"id":"523","regency_id":"240","name":"Astanajapura"},{"id":"1097","regency_id":"240","name":"Gempol"},{"id":"1250","regency_id":"240","name":"Ciledug"},{"id":"1398","regency_id":"240","name":"Gebang"},{"id":"1533","regency_id":"240","name":"Gunung Jati (Cirebon Utara)"},{"id":"1555","regency_id":"240","name":"Depok"},{"id":"1556","regency_id":"240","name":"Ciwaringin"},{"id":"1601","regency_id":"240","name":"Gegesik"},{"id":"1659","regency_id":"240","name":"Dukupuntang"},{"id":"1688","regency_id":"240","name":"Jamblang"},{"id":"1743","regency_id":"240","name":"Greged (Greget)"},{"id":"2046","regency_id":"240","name":"Kaliwedi"},{"id":"2085","regency_id":"240","name":"Kapetakan"},{"id":"2291","regency_id":"240","name":"Kedawung"},{"id":"2468","regency_id":"240","name":"Karangsembung"},{"id":"2502","regency_id":"240","name":"Karangwareng"},{"id":"2916","regency_id":"240","name":"Klangenan"},{"id":"3237","regency_id":"240","name":"Lemahabang"},{"id":"3660","regency_id":"240","name":"Losari"},{"id":"3912","regency_id":"240","name":"Palimanan"},{"id":"3934","regency_id":"240","name":"Pangenan"},{"id":"3944","regency_id":"240","name":"Mundu"},{"id":"4117","regency_id":"240","name":"Panguragan"},{"id":"4547","regency_id":"240","name":"Pabedilan"},{"id":"4642","regency_id":"240","name":"Pabuaran"},{"id":"4721","regency_id":"240","name":"Pasaleman"},{"id":"5052","regency_id":"240","name":"Plered"},{"id":"5139","regency_id":"240","name":"Plumbon"},{"id":"5450","regency_id":"240","name":"Sedong"},{"id":"5710","regency_id":"240","name":"Talun (Cirebon Selatan)"},{"id":"5868","regency_id":"240","name":"Suranenggala"},{"id":"6016","regency_id":"240","name":"Susukan"},{"id":"6031","regency_id":"240","name":"Sumber"},{"id":"6196","regency_id":"240","name":"Susukan Lebak"},{"id":"6563","regency_id":"240","name":"Waled"},{"id":"6618","regency_id":"240","name":"Tengah Tani"},{"id":"6712","regency_id":"240","name":"Weru"}]