[{"id":"375","regency_id":"506","name":"Babakancikao"},{"id":"733","regency_id":"506","name":"Campaka"},{"id":"838","regency_id":"506","name":"Bungursari"},{"id":"980","regency_id":"506","name":"Bojong"},{"id":"1010","regency_id":"506","name":"Cibatu"},{"id":"1567","regency_id":"506","name":"Jatiluhur"},{"id":"1735","regency_id":"506","name":"Darangdan"},{"id":"2534","regency_id":"506","name":"Kiarapedes"},{"id":"4027","regency_id":"506","name":"Maniis"},{"id":"4187","regency_id":"506","name":"Pasawahan"},{"id":"5080","regency_id":"506","name":"Plered"},{"id":"5133","regency_id":"506","name":"Pondoksalam"},{"id":"5197","regency_id":"506","name":"Purwakarta"},{"id":"6229","regency_id":"506","name":"Sukasari"},{"id":"6355","regency_id":"506","name":"Sukatani"},{"id":"6559","regency_id":"506","name":"Tegalwaru (Tegal Waru)"},{"id":"6914","regency_id":"506","name":"Wanayasa"}]